magic_rs/__init__.py
magic_rs/__version__.py
magic_rs/_magic_rs.pyi
magic_rs/_magic_rs.pypy311-pp73-x86_64-linux-gnu.so
magic_rs/py.typed
magic_rs-0.3.0.dist-info/METADATA
magic_rs-0.3.0.dist-info/WHEEL
magic_rs-0.3.0.dist-info/licenses/LICENSE
magic_rs-0.3.0.dist-info/RECORD
