Metadata-Version: 2.4
Name: magic-rs
Version: 0.3.0
Classifier: Development Status :: 5 - Production/Stable
Classifier: Intended Audience :: Developers
Classifier: License :: OSI Approved :: MIT License
Classifier: Operating System :: MacOS
Classifier: Operating System :: Microsoft :: Windows
Classifier: Operating System :: POSIX :: Linux
Classifier: Programming Language :: Python :: 3
Classifier: Programming Language :: Python :: 3.9
Classifier: Programming Language :: Python :: 3.10
Classifier: Programming Language :: Python :: 3.11
Classifier: Programming Language :: Python :: 3.12
Classifier: Programming Language :: Python :: 3.13
Classifier: Programming Language :: Python :: 3.14
Classifier: Programming Language :: Python :: Implementation :: CPython
Classifier: Programming Language :: Python :: Implementation :: PyPy
Classifier: Programming Language :: Python
Classifier: Programming Language :: Rust
Classifier: Topic :: Software Development :: Libraries :: Python Modules
Requires-Dist: pytest>=8.3.0 ; extra == 'test'
Provides-Extra: test
License-File: LICENSE
Summary: Use rust infer crate to rewrite python-magic library
Keywords: filetype,mime,libmagic
Home-Page: https://github.com/rp-libs/magic-rs
Author-email: vvanglro <vvanglro@gmail.com>
License: MIT
Requires-Python: >=3.9
Project-URL: Funding, https://github.com/rp-libs/magic-rs
Project-URL: Homepage, https://github.com/rp-libs/magic-rs
Project-URL: Source, https://github.com/rp-libs/magic-rs
